idingtalk/__init__.py
idingtalk/incoming.py
idingtalk-0.0.5.dist-info/LICENSE
idingtalk-0.0.5.dist-info/METADATA
idingtalk-0.0.5.dist-info/WHEEL
idingtalk-0.0.5.dist-info/top_level.txt
idingtalk-0.0.5.dist-info/RECORD
