Metadata-Version: 2.1
Name: idingtalk
Version: 0.0.5
Summary: Dingtalk tools.
Home-page: https://pypi.org/project/idingtalk/
Author: teachmyself
Author-email: teachmyself@126.com
License: MIT
Keywords: idingtalk,Dingding,DingTalk,incoming
Platform: UNKNOWN
Classifier: Development Status :: 5 - Production/Stable
Classifier: Operating System :: OS Independent
Classifier: Intended Audience :: Developers
Classifier: License :: OSI Approved :: MIT License
Classifier: Programming Language :: Python :: 2.7
Classifier: Programming Language :: Python :: 3.4
Requires-Dist: requests
